contexts/__init__.py
contexts/default_context.py
lavague/tests/__init__.py
lavague/tests/cli.py
lavague/tests/config.py
lavague/tests/runner.py
lavague/tests/setup.py
lavague/tests/test.py
lavague_tests-0.0.4.dist-info/METADATA
lavague_tests-0.0.4.dist-info/WHEEL
lavague_tests-0.0.4.dist-info/entry_points.txt
lavague_tests-0.0.4.dist-info/RECORD
